pypoligram/__init__.py
pypoligram/arg_types.py
pypoligram/clients.py
pypoligram/dispatcher.py
pypoligram/filters.py
pypoligram/sync.py
pypoligram/decorators/__init__.py
pypoligram/decorators/on_callback_query.py
pypoligram/decorators/on_chat_boost.py
pypoligram/decorators/on_chat_join_request.py
pypoligram/decorators/on_chat_member_updated.py
pypoligram/decorators/on_chosen_inline_result.py
pypoligram/decorators/on_deleted_messages.py
pypoligram/decorators/on_disconnect.py
pypoligram/decorators/on_edited_message.py
pypoligram/decorators/on_inline_query.py
pypoligram/decorators/on_message.py
pypoligram/decorators/on_message_reaction.py
pypoligram/decorators/on_message_reaction_count.py
pypoligram/decorators/on_poll.py
pypoligram/decorators/on_pre_checkout_query.py
pypoligram/decorators/on_purchased_paid_media.py
pypoligram/decorators/on_raw_update.py
pypoligram/decorators/on_shipping_query.py
pypoligram/decorators/on_story.py
pypoligram/decorators/on_user_status.py
pypoligram-0.2.1.dist-info/METADATA
pypoligram-0.2.1.dist-info/WHEEL
pypoligram-0.2.1.dist-info/licenses/COPYING
pypoligram-0.2.1.dist-info/licenses/COPYING.lesser
pypoligram-0.2.1.dist-info/RECORD
