Metadata-Version: 2.4
Name: pypoligram
Version: 0.2.1
Summary: Simplifies the process of handling multiple clients
Project-URL: Homepage, https://github.com/MemoKing34/pypoligram
Project-URL: Repository, https://github.com/MemoKing34/pypoligram
Project-URL: Documentation, https://github.com/MemoKing34/pypoligram/blob/main/DOCUMENTATION.md
Author-email: MemoKing34 <karam24@itu.edu.tr>
License:                    GNU LESSER GENERAL PUBLIC LICENSE
License-File: COPYING
License-File: COPYING.lesser
Requires-Python: >=3.12
Provides-Extra: dev
Requires-Dist: kurigram>=2.2.1; extra == 'dev'
